slidepyv6/__init__.py
slidepyv6/core.py
slidepyv6/io/__init__.py
slidepyv6/io/io.py
slidepyv6/io/parsers/__init__.py
slidepyv6/io/parsers/input_parser.py
slidepyv6/io/parsers/output_parser.py
slidepyv6/models/__init__.py
slidepyv6/models/geometries.py
slidepyv6/models/loads.py
slidepyv6/models/metadata.py
slidepyv6/models/properties.py
slidepyv6/models/results.py
slidepyv6/utils/__init__.py
slidepyv6/utils/exceptions.py
slidepyv6/utils/utils.py
slidepyv6-0.1.5.dist-info/licenses/LICENSE .txt
slidepyv6-0.1.5.dist-info/METADATA
slidepyv6-0.1.5.dist-info/WHEEL
slidepyv6-0.1.5.dist-info/top_level.txt
slidepyv6-0.1.5.dist-info/RECORD
