Metadata-Version: 2.4
Name: slidepyv6
Version: 0.1.5
Summary: Librería para leer y analizar archivos de proyectos geotécnicos en formato .SLIM de Slide V6 (Rocscience)
Home-page: https://github.com/edwinar13/SlidePyV6-Library
Author: Edwin Arevalo
Author-email: terrioingeniera@gmail.com
Classifier: Programming Language :: Python :: 3
Classifier: License :: OSI Approved :: MIT License
Classifier: Operating System :: OS Independent
Requires-Python: >=3.9
License-File: LICENSE .txt
Dynamic: author
Dynamic: author-email
Dynamic: classifier
Dynamic: description
Dynamic: description-content-type
Dynamic: home-page
Dynamic: license-file
Dynamic: requires-python
Dynamic: summary
